__init__.py
apsarea.py
apsarea-0.0.3.dist-info/LICENSE.txt
apsarea-0.0.3.dist-info/METADATA
apsarea-0.0.3.dist-info/WHEEL
apsarea-0.0.3.dist-info/top_level.txt
apsarea-0.0.3.dist-info/RECORD
