Metadata-Version: 2.1
Name: apsarea
Version: 0.0.3
Summary: module to calculate area
Author-email: Santin Fabrizio <apstechinfo20@gmail.com>
Project-URL: Homepage, https://github.com/pypa/sampleproject
Project-URL: Issues, https://github.com/pypa/sampleproject/issues
Classifier: Programming Language :: Python :: 3
Classifier: License :: OSI Approved :: MIT License
Classifier: Operating System :: OS Independent
Requires-Python: >=3.6
License-File: LICENSE.txt
